bump_semver_anywhere/__init__.py
bump_semver_anywhere/__main__.py
bump_semver_anywhere/app.py
bump_semver_anywhere/cli.py
bump_semver_anywhere-0.3.0.dist-info/entry_points.txt
bump_semver_anywhere-0.3.0.dist-info/WHEEL
bump_semver_anywhere-0.3.0.dist-info/METADATA
bump_semver_anywhere-0.3.0.dist-info/RECORD
