Metadata-Version: 2.1
Name: bump-semver-anywhere
Version: 0.3.0
Summary: Bump your semantic version of any software using regex
Home-page: https://github.com/scratchmex/all-relative
Author: Ivan Gonzalez
Author-email: scratchmex@gmail.com
Requires-Python: >=3.8,<4.0
Classifier: Programming Language :: Python :: 3
Classifier: Programming Language :: Python :: 3.10
Classifier: Programming Language :: Python :: 3.8
Classifier: Programming Language :: Python :: 3.9
Requires-Dist: click (>=8.0.3,<9.0.0)
Requires-Dist: pydantic (>=1.8.2,<2.0.0)
Requires-Dist: pytomlpp (>=1.0.3,<2.0.0)
Requires-Dist: semver (>=2.13.0,<3.0.0)
Project-URL: Repository, https://github.com/scratchmex/all-relative
